rotunicode/__init__.py
rotunicode/console_scripts.py
rotunicode/rotunicode.py
rotunicode/utils.py
rotunicode-2.3.0.dist-info/LICENSE
rotunicode-2.3.0.dist-info/METADATA
rotunicode-2.3.0.dist-info/WHEEL
rotunicode-2.3.0.dist-info/entry_points.txt
rotunicode-2.3.0.dist-info/top_level.txt
rotunicode-2.3.0.dist-info/RECORD
